yummy_delta-0.0.9.dist-info/METADATA
yummy_delta-0.0.9.dist-info/WHEEL
yummy_delta-0.0.9.dist-info/license_files/LICENSE
yummy_delta.libs/libssl-f8da170d.so.1.1
yummy_delta.libs/libcrypto-75174c47.so.1.1
yummy_delta.libs/liblzma-3f0fbaca.so.5
yummy_delta/__init__.py
yummy_delta/yummy_delta.cpython-39-x86_64-linux-gnu.so
yummy_delta-0.0.9.dist-info/RECORD
